{
  "version": "3.16.1",
  "flags": {},
  "shapes": [
    {
      "label": "obstruction",
      "line_color": null,
      "fill_color": null,
      "points": [
        [
          613.3333333333334,
          568.8888888888889
        ],
        [
          638.8888888888889,
          566.6666666666666
        ],
        [
          653.3333333333334,
          561.1111111111111
        ],
        [
          664.4444444444445,
          561.1111111111111
        ],
        [
          672.2222222222222,
          558.8888888888889
        ],
        [
          674.4444444444445,
          553.3333333333334
        ],
        [
          677.7777777777777,
          551.1111111111111
        ],
        [
          664.4444444444445,
          535.5555555555555
        ],
        [
          652.2222222222222,
          531.1111111111111
        ],
        [
          612.2222222222222,
          556.6666666666666
        ]
      ],
      "shape_type": "polygon",
      "flags": {}
    },
    {
      "label": "muddy road",
      "line_color": null,
      "fill_color": null,
      "points": [
        [
          1321.111111111111,
          637.7777777777777
        ],
        [
          1256.6666666666667,
          634.4444444444445
        ],
        [
          1205.5555555555554,
          630.0
        ],
        [
          1188.888888888889,
          627.7777777777777
        ],
        [
          1187.7777777777778,
          613.3333333333334
        ],
        [
          1207.7777777777778,
          608.8888888888889
        ],
        [
          1256.6666666666667,
          606.6666666666666
        ],
        [
          1298.888888888889,
          610.0
        ],
        [
          1331.111111111111,
          621.1111111111111
        ]
      ],
      "shape_type": "polygon",
      "flags": {}
    },
    {
      "label": "muddy road",
      "line_color": null,
      "fill_color": null,
      "points": [
        [
          1357.7777777777778,
          624.4444444444445
        ],
        [
          1322.2222222222222,
          640.0
        ],
        [
          2046.6666666666665,
          835.5555555555555
        ],
        [
          2044.4444444444443,
          757.7777777777777
        ]
      ],
      "shape_type": "polygon",
      "flags": {}
    }
  ],
  "lineColor": [
    0,
    255,
    0,
    128
  ],
  "fillColor": [
    255,
    0,
    0,
    128
  ],
  "imagePath": "Pictures2250_leftImg8bit.png",
  "imageData": null,
  "imageHeight": 1024,
  "imageWidth": 2048
}