{
  "version": "3.16.7",
  "flags": {},
  "shapes": [
    {
      "label": "sideroad",
      "line_color": null,
      "fill_color": null,
      "points": [
        [
          504.0,
          850.5
        ],
        [
          562.5,
          736.0
        ],
        [
          565.5,
          727.0
        ],
        [
          569.5,
          721.0
        ],
        [
          573.5,
          710.0
        ],
        [
          578.5,
          702.0
        ],
        [
          582.5,
          691.0
        ],
        [
          587.5,
          683.0
        ],
        [
          614.5,
          625.0
        ],
        [
          629.5,
          536.0
        ],
        [
          629.0,
          533.5
        ],
        [
          621.0,
          529.5
        ],
        [
          617.0,
          525.5
        ],
        [
          601.0,
          517.5
        ],
        [
          579.0,
          512.5
        ],
        [
          577.0,
          510.5
        ],
        [
          554.0,
          504.5
        ],
        [
          553.5,
          521.0
        ],
        [
          551.5,
          522.0
        ],
        [
          553.5,
          524.0
        ],
        [
          553.5,
          533.0
        ],
        [
          551.5,
          534.0
        ],
        [
          551.5,
          555.0
        ],
        [
          549.5,
          556.0
        ],
        [
          549.5,
          563.0
        ],
        [
          547.5,
          564.0
        ],
        [
          547.5,
          571.0
        ],
        [
          543.5,
          572.0
        ],
        [
          543.5,
          575.0
        ],
        [
          535.0,
          583.5
        ],
        [
          514.0,
          583.5
        ],
        [
          513.0,
          581.5
        ],
        [
          509.5,
          581.0
        ],
        [
          509.0,
          577.5
        ],
        [
          504.0,
          577.5
        ],
        [
          501.5,
          580.0
        ],
        [
          501.5,
          583.0
        ],
        [
          499.5,
          584.0
        ],
        [
          499.5,
          587.0
        ],
        [
          495.0,
          591.5
        ],
        [
          492.0,
          591.5
        ],
        [
          491.5,
          595.0
        ],
        [
          488.0,
          595.5
        ],
        [
          487.0,
          597.5
        ],
        [
          478.0,
          597.5
        ],
        [
          477.0,
          595.5
        ],
        [
          470.0,
          595.5
        ],
        [
          465.0,
          589.5
        ],
        [
          462.0,
          589.5
        ],
        [
          461.5,
          584.0
        ],
        [
          454.0,
          581.5
        ],
        [
          449.5,
          577.0
        ],
        [
          449.5,
          574.0
        ],
        [
          447.5,
          572.0
        ],
        [
          449.5,
          570.0
        ],
        [
          443.0,
          563.5
        ],
        [
          420.0,
          563.5
        ],
        [
          415.0,
          567.5
        ],
        [
          412.0,
          567.5
        ],
        [
          411.0,
          569.5
        ],
        [
          408.0,
          569.5
        ],
        [
          407.0,
          571.5
        ],
        [
          404.0,
          571.5
        ],
        [
          403.0,
          573.5
        ],
        [
          384.0,
          573.5
        ],
        [
          382.0,
          571.5
        ],
        [
          380.0,
          573.5
        ],
        [
          371.5,
          567.0
        ],
        [
          371.5,
          564.0
        ],
        [
          367.0,
          559.5
        ],
        [
          348.0,
          559.5
        ],
        [
          345.5,
          562.0
        ],
        [
          345.5,
          567.0
        ],
        [
          343.5,
          568.0
        ],
        [
          347.5,
          571.0
        ],
        [
          338.0,
          571.5
        ],
        [
          335.5,
          574.0
        ],
        [
          335.5,
          577.0
        ],
        [
          333.5,
          578.0
        ],
        [
          333.5,
          581.0
        ],
        [
          327.0,
          587.5
        ],
        [
          312.0,
          589.5
        ],
        [
          311.0,
          587.5
        ],
        [
          302.0,
          587.5
        ],
        [
          295.5,
          579.0
        ],
        [
          295.5,
          572.0
        ],
        [
          293.5,
          571.0
        ],
        [
          293.5,
          562.0
        ],
        [
          291.5,
          561.0
        ],
        [
          293.5,
          558.0
        ],
        [
          291.5,
          557.0
        ],
        [
          291.5,
          552.0
        ],
        [
          287.5,
          551.0
        ],
        [
          287.0,
          547.5
        ],
        [
          272.0,
          547.5
        ],
        [
          271.0,
          549.5
        ],
        [
          260.0,
          549.5
        ],
        [
          258.0,
          547.5
        ],
        [
          256.0,
          549.5
        ],
        [
          255.5,
          546.0
        ],
        [
          254.0,
          545.5
        ],
        [
          253.0,
          547.5
        ],
        [
          244.0,
          547.5
        ],
        [
          243.5,
          551.0
        ],
        [
          239.5,
          552.0
        ],
        [
          239.0,
          555.5
        ],
        [
          235.5,
          556.0
        ],
        [
          235.5,
          559.0
        ],
        [
          231.0,
          563.5
        ],
        [
          224.0,
          563.5
        ],
        [
          223.0,
          567.5
        ],
        [
          218.0,
          567.5
        ],
        [
          219.0,
          571.5
        ],
        [
          212.0,
          571.5
        ],
        [
          211.0,
          575.5
        ],
        [
          202.0,
          575.5
        ],
        [
          199.0,
          579.5
        ],
        [
          184.0,
          581.5
        ],
        [
          183.0,
          583.5
        ],
        [
          164.0,
          583.5
        ],
        [
          163.0,
          581.5
        ],
        [
          156.0,
          581.5
        ],
        [
          155.0,
          579.5
        ],
        [
          136.0,
          577.5
        ],
        [
          137.0,
          573.5
        ],
        [
          128.0,
          573.5
        ],
        [
          127.0,
          577.5
        ],
        [
          124.0,
          577.5
        ],
        [
          123.0,
          575.5
        ],
        [
          112.0,
          575.5
        ],
        [
          111.5,
          572.0
        ],
        [
          108.0,
          571.5
        ],
        [
          107.0,
          569.5
        ],
        [
          101.0,
          575.5
        ],
        [
          94.0,
          575.5
        ],
        [
          91.0,
          571.5
        ],
        [
          88.0,
          571.5
        ],
        [
          83.0,
          575.5
        ],
        [
          80.0,
          573.5
        ],
        [
          78.0,
          575.5
        ],
        [
          77.0,
          571.5
        ],
        [
          70.0,
          571.5
        ],
        [
          69.0,
          569.5
        ],
        [
          64.0,
          569.5
        ],
        [
          63.0,
          571.5
        ],
        [
          48.0,
          571.5
        ],
        [
          47.0,
          567.5
        ],
        [
          28.0,
          567.5
        ],
        [
          27.0,
          571.5
        ],
        [
          23.5,
          572.0
        ],
        [
          23.0,
          575.5
        ],
        [
          8.0,
          575.5
        ],
        [
          7.0,
          571.5
        ],
        [
          3.5,
          571.0
        ],
        [
          3.5,
          560.0
        ],
        [
          0.5,
          560.0
        ],
        [
          2.5,
          593.0
        ],
        [
          2.5,
          651.0
        ],
        [
          7.5,
          650.0
        ],
        [
          7.5,
          657.0
        ],
        [
          4.0,
          657.5
        ],
        [
          2.5,
          654.0
        ],
        [
          0.0,
          846.5
        ],
        [
          143.0,
          846.5
        ],
        [
          216.0,
          848.5
        ],
        [
          504.0,
          850.5
        ]
      ],
      "shape_type": "polygon",
      "flags": {}
    },
    {
      "label": "roughroadpatch",
      "line_color": null,
      "fill_color": null,
      "points": [
        [
          613.0,
          523.5
        ],
        [
          602.0,
          512.5
        ],
        [
          586.5,
          514.0
        ],
        [
          604.0,
          518.5
        ],
        [
          613.0,
          523.5
        ]
      ],
      "shape_type": "polygon",
      "flags": {}
    },
    {
      "label": "pothole",
      "line_color": null,
      "fill_color": null,
      "points": [
        [
          629.0,
          654.5
        ],
        [
          719.0,
          650.5
        ],
        [
          769.0,
          650.5
        ],
        [
          769.5,
          645.0
        ],
        [
          654.0,
          633.5
        ],
        [
          648.0,
          629.5
        ],
        [
          636.0,
          625.5
        ],
        [
          633.0,
          633.5
        ],
        [
          611.0,
          633.5
        ],
        [
          602.5,
          650.0
        ],
        [
          604.0,
          651.5
        ],
        [
          629.0,
          654.5
        ]
      ],
      "shape_type": "polygon",
      "flags": {}
    }
  ],
  "lineColor": [
    0,
    255,
    0,
    128
  ],
  "fillColor": [
    255,
    0,
    0,
    128
  ],
  "imagePath": "Pictures1371_leftImg8bit.png",
  "imageData": null,
  "imageHeight": 1024,
  "imageWidth": 2048
}