{
  "version": "3.16.1",
  "flags": {},
  "shapes": [
    {
      "label": "pothole",
      "line_color": null,
      "fill_color": null,
      "points": [
        [
          1618.0526315789473,
          645.7894736842105
        ],
        [
          1644.3684210526314,
          666.8421052631579
        ],
        [
          1704.8947368421052,
          666.8421052631579
        ],
        [
          1729.8947368421052,
          657.6315789473684
        ],
        [
          1675.9473684210527,
          643.1578947368421
        ]
      ],
      "shape_type": "polygon",
      "flags": {}
    },
    {
      "label": "rough road",
      "line_color": null,
      "fill_color": null,
      "points": [
        [
          706.2105263157895,
          603.6842105263158
        ],
        [
          757.5263157894736,
          639.2105263157895
        ],
        [
          1141.7368421052631,
          640.5263157894736
        ],
        [
          1203.578947368421,
          610.2631578947369
        ],
        [
          929.8947368421052,
          585.2631578947369
        ]
      ],
      "shape_type": "polygon",
      "flags": {}
    }
  ],
  "lineColor": [
    0,
    255,
    0,
    128
  ],
  "fillColor": [
    255,
    0,
    0,
    128
  ],
  "imagePath": "Pictures1026_leftImg8bit.png",
  "imageData": null,
  "imageHeight": 1024,
  "imageWidth": 2048
}