{
  "version": "3.16.7",
  "flags": {},
  "shapes": [
    {
      "label": "wetroadpatch",
      "line_color": null,
      "fill_color": null,
      "points": [
        [
          93.0,
          877.5
        ],
        [
          150.0,
          859.5
        ],
        [
          198.0,
          850.5
        ],
        [
          210.5,
          837.0
        ],
        [
          210.5,
          828.0
        ],
        [
          202.0,
          812.5
        ],
        [
          168.0,
          809.5
        ],
        [
          111.0,
          808.5
        ],
        [
          110.5,
          811.0
        ],
        [
          112.5,
          813.0
        ],
        [
          113.5,
          820.0
        ],
        [
          109.0,
          826.5
        ],
        [
          57.0,
          849.5
        ],
        [
          54.5,
          856.0
        ],
        [
          53.0,
          865.5
        ],
        [
          93.0,
          877.5
        ]
      ],
      "shape_type": "polygon",
      "flags": {}
    },
    {
      "label": "pothole",
      "line_color": null,
      "fill_color": null,
      "points": [
        [
          635.0,
          838.5
        ],
        [
          677.5,
          837.0
        ],
        [
          673.0,
          825.5
        ],
        [
          656.0,
          820.5
        ],
        [
          644.0,
          819.5
        ],
        [
          579.0,
          816.5
        ],
        [
          540.0,
          816.5
        ],
        [
          518.0,
          814.5
        ],
        [
          439.0,
          813.5
        ],
        [
          387.0,
          805.5
        ],
        [
          334.0,
          805.5
        ],
        [
          297.0,
          801.5
        ],
        [
          274.5,
          808.0
        ],
        [
          274.5,
          814.0
        ],
        [
          277.0,
          816.5
        ],
        [
          291.0,
          820.5
        ],
        [
          310.0,
          828.5
        ],
        [
          400.0,
          830.5
        ],
        [
          419.0,
          832.5
        ],
        [
          599.0,
          838.5
        ],
        [
          635.0,
          838.5
        ]
      ],
      "shape_type": "polygon",
      "flags": {}
    },
    {
      "label": "bump",
      "line_color": null,
      "fill_color": null,
      "points": [
        [
          902.0,
          581.5
        ],
        [
          905.5,
          580.0
        ],
        [
          905.5,
          573.0
        ],
        [
          902.0,
          569.5
        ],
        [
          819.5,
          570.0
        ],
        [
          820.0,
          580.5
        ],
        [
          902.0,
          581.5
        ]
      ],
      "shape_type": "polygon",
      "flags": {}
    }
  ],
  "lineColor": [
    0,
    255,
    0,
    128
  ],
  "fillColor": [
    255,
    0,
    0,
    128
  ],
  "imagePath": "Pictures1505_leftImg8bit.png",
  "imageData": null,
  "imageHeight": 1024,
  "imageWidth": 2048
}