{
  "version": "3.16.1",
  "flags": {},
  "shapes": [
    {
      "label": "waterlog",
      "line_color": [
        51,
        51,
        255,
        128
      ],
      "fill_color": null,
      "points": [
        [
          432.1052631578949,
          1016.842105263158
        ],
        [
          583.421052631579,
          889.2105263157894
        ],
        [
          647.8947368421052,
          760.2631578947368
        ],
        [
          741.3157894736837,
          677.3684210526314
        ],
        [
          878.1578947368421,
          608.9473684210526
        ],
        [
          865.0,
          716.8421052631579
        ],
        [
          741.3157894736837,
          768.1578947368421
        ],
        [
          809.7368421052622,
          795.7894736842104
        ],
        [
          600.5263157894736,
          1014.2105263157895
        ]
      ],
      "shape_type": "polygon",
      "flags": {}
    },
    {
      "label": "wet road",
      "line_color": [
        80,
        200,
        255,
        128
      ],
      "fill_color": null,
      "points": [
        [
          900.5263157894738,
          607.6315789473683
        ],
        [
          978.1578947368423,
          601.0526315789473
        ],
        [
          997.8947368421054,
          573.4210526315788
        ],
        [
          1326.842105263158,
          748.421052631579
        ],
        [
          1411.0526315789473,
          786.578947368421
        ],
        [
          1630.7894736842104,
          986.578947368421
        ],
        [
          1561.0526315789457,
          1002.3684210526317
        ],
        [
          668.9473684210526,
          987.8947368421052
        ],
        [
          959.7368421052633,
          723.4210526315788
        ]
      ],
      "shape_type": "polygon",
      "flags": {}
    }
  ],
  "lineColor": [
    0,
    255,
    0,
    128
  ],
  "fillColor": [
    255,
    0,
    0,
    128
  ],
  "imagePath": "Pictures2313_leftImg8bit.png",
  "imageData": null,
  "imageHeight": 1024,
  "imageWidth": 2048
}