{
  "version": "3.16.1",
  "flags": {},
  "shapes": [
    {
      "label": "obstruction",
      "line_color": null,
      "fill_color": null,
      "points": [
        [
          426.57894736842104,
          679.7894736842105
        ],
        [
          401.57894736842104,
          674.5263157894736
        ],
        [
          364.7368421052632,
          667.9473684210526
        ],
        [
          333.1578947368421,
          662.6842105263157
        ],
        [
          313.42105263157896,
          660.0526315789474
        ],
        [
          293.6842105263158,
          658.7368421052631
        ],
        [
          277.89473684210526,
          657.421052631579
        ],
        [
          255.5263157894737,
          654.7894736842105
        ],
        [
          235.78947368421052,
          653.4736842105264
        ],
        [
          222.6315789473684,
          649.5263157894736
        ],
        [
          213.42105263157893,
          642.9473684210526
        ],
        [
          201.57894736842104,
          640.3157894736842
        ],
        [
          175.26315789473685,
          635.0526315789474
        ],
        [
          152.89473684210526,
          636.3684210526316
        ],
        [
          162.10526315789474,
          645.578947368421
        ],
        [
          181.8421052631579,
          648.2105263157895
        ],
        [
          201.57894736842104,
          654.7894736842105
        ],
        [
          212.10526315789474,
          658.7368421052631
        ],
        [
          226.57894736842104,
          664.0
        ],
        [
          246.31578947368422,
          667.9473684210526
        ],
        [
          259.4736842105263,
          667.9473684210526
        ],
        [
          268.6842105263158,
          669.2631578947369
        ],
        [
          279.2105263157895,
          671.8947368421052
        ],
        [
          291.05263157894734,
          671.8947368421052
        ],
        [
          302.89473684210526,
          674.5263157894736
        ],
        [
          318.6842105263158,
          675.8421052631579
        ],
        [
          330.5263157894737,
          679.7894736842105
        ],
        [
          347.63157894736844,
          679.7894736842105
        ],
        [
          360.7894736842105,
          683.7368421052631
        ],
        [
          380.5263157894737,
          685.0526315789474
        ],
        [
          404.2105263157895,
          686.3684210526316
        ]
      ],
      "shape_type": "polygon",
      "flags": {}
    },
    {
      "label": "pothole",
      "line_color": null,
      "fill_color": null,
      "points": [
        [
          827.8947368421052,
          578.4736842105264
        ],
        [
          817.3684210526316,
          573.2105263157895
        ],
        [
          801.578947368421,
          566.6315789473684
        ],
        [
          788.421052631579,
          564.0
        ],
        [
          780.5263157894736,
          562.6842105263158
        ],
        [
          779.2105263157895,
          574.5263157894736
        ],
        [
          789.7368421052631,
          577.1578947368421
        ],
        [
          800.2631578947369,
          579.7894736842105
        ],
        [
          812.1052631578947,
          583.7368421052631
        ]
      ],
      "shape_type": "polygon",
      "flags": {}
    },
    {
      "label": "rough road",
      "line_color": null,
      "fill_color": null,
      "points": [
        [
          2.894736842105263,
          804.7894736842105
        ],
        [
          420.0,
          673.2105263157895
        ],
        [
          164.73684210526315,
          627.1578947368421
        ],
        [
          2.894736842105263,
          640.3157894736842
        ]
      ],
      "shape_type": "polygon",
      "flags": {}
    }
  ],
  "lineColor": [
    0,
    255,
    0,
    128
  ],
  "fillColor": [
    255,
    0,
    0,
    128
  ],
  "imagePath": "Pictures1328_leftImg8bit.png",
  "imageData": null,
  "imageHeight": 1024,
  "imageWidth": 2048
}