{
  "version": "3.16.1",
  "flags": {},
  "shapes": [
    {
      "label": "side road",
      "line_color": null,
      "fill_color": null,
      "points": [
        [
          26.444444444444443,
          1018.2222222222222
        ],
        [
          1002.0,
          560.4444444444445
        ],
        [
          1002.0,
          542.6666666666666
        ],
        [
          950.8888888888889,
          538.2222222222222
        ],
        [
          0,
          825
        ],
        [
          0,
          1023
        ]
      ],
      "shape_type": "polygon",
      "flags": {}
    },
    {
      "label": "muddy road",
      "line_color": null,
      "fill_color": null,
      "points": [
        [
          26.444444444444443,
          1018.2222222222222
        ],
        [
          644.2222222222222,
          1013.7777777777778
        ],
        [
          1019.7777777777778,
          591.5555555555555
        ],
        [
          1004.2222222222222,
          564.8888888888889
        ]
      ],
      "shape_type": "polygon",
      "flags": {}
    },
    {
      "label": "pothole",
      "line_color": null,
      "fill_color": null,
      "points": [
        [
          1434.920634920635,
          798.4126984126984
        ],
        [
          1311.111111111111,
          807.936507936508
        ],
        [
          1225.3968253968253,
          788.8888888888889
        ],
        [
          1236.5079365079364,
          768.2539682539682
        ],
        [
          1269.8412698412699,
          765.0793650793651
        ],
        [
          1320.6349206349207,
          765.0793650793651
        ],
        [
          1360.3174603174602,
          761.9047619047619
        ],
        [
          1409.5238095238094,
          763.4920634920635
        ]
      ],
      "shape_type": "polygon",
      "flags": {}
    },
    {
      "label": "pothole",
      "line_color": null,
      "fill_color": null,
      "points": [
        [
          1047.6190476190477,
          779.3650793650794
        ],
        [
          1014.2857142857143,
          780.952380952381
        ],
        [
          979.3650793650794,
          780.952380952381
        ],
        [
          958.7301587301587,
          776.1904761904761
        ],
        [
          958.7301587301587,
          757.1428571428571
        ],
        [
          988.8888888888889,
          742.8571428571429
        ],
        [
          1017.4603174603175,
          749.2063492063492
        ],
        [
          1050.7936507936508,
          753.968253968254
        ],
        [
          1068.2539682539682,
          760.3174603174604
        ]
      ],
      "shape_type": "polygon",
      "flags": {}
    },
    {
      "label": "rough road",
      "line_color": null,
      "fill_color": null,
      "points": [
        [
          1042.857142857143,
          1011.1111111111111
        ],
        [
          684.1269841269841,
          955.5555555555555
        ],
        [
          801.5873015873016,
          780.952380952381
        ],
        [
          949.2063492063492,
          780.952380952381
        ],
        [
          1012.6984126984127,
          790.4761904761905
        ],
        [
          1404.7619047619048,
          830.1587301587301
        ],
        [
          1615.873015873016,
          828.5714285714286
        ],
        [
          1900.0,
          955.5555555555555
        ],
        [
          1958.7301587301588,
          1020.6349206349206
        ]
      ],
      "shape_type": "polygon",
      "flags": {}
    },
    {
      "label": "side road",
      "line_color": null,
      "fill_color": null,
      "points": [
        [
          1569.8412698412699,
          657.1428571428571
        ],
        [
          1655.5555555555557,
          642.8571428571429
        ],
        [
          2039.6825396825398,
          779.3650793650794
        ],
        [
          2042.857142857143,
          950.7936507936508
        ]
      ],
      "shape_type": "polygon",
      "flags": {}
    },
    {
      "label": "muddy road",
      "line_color": null,
      "fill_color": null,
      "points": [
        [
          2046.031746031746,
          957.1428571428571
        ],
        [
          2042.857142857143,
          1022.2222222222222
        ],
        [
          1957.142857142857,
          1019.047619047619
        ],
        [
          1904.7619047619048,
          963.4920634920635
        ],
        [
          1623.8095238095239,
          826.984126984127
        ],
        [
          1387.3015873015872,
          661.9047619047619
        ],
        [
          1573.015873015873,
          653.968253968254
        ]
      ],
      "shape_type": "polygon",
      "flags": {}
    },
    {
      "label": "waterlog",
      "line_color": null,
      "fill_color": null,
      "points": [
        [
          957.3170731707316,
          578.0487804878048
        ],
        [
          915.8536585365853,
          571.951219512195
        ],
        [
          913.4146341463414,
          562.1951219512194
        ],
        [
          941.4634146341463,
          559.7560975609756
        ],
        [
          967.0731707317073,
          558.5365853658536
        ],
        [
          987.8048780487804,
          560.9756097560975
        ],
        [
          995.1219512195121,
          564.6341463414634
        ]
      ],
      "shape_type": "polygon",
      "flags": {}
    },
    {
      "label": "waterlog",
      "line_color": null,
      "fill_color": null,
      "points": [
        [
          792.6829268292682,
          606.0975609756097
        ],
        [
          820.7317073170731,
          608.5365853658536
        ],
        [
          845.1219512195121,
          603.6585365853658
        ],
        [
          840.2439024390243,
          592.6829268292682
        ],
        [
          809.7560975609756,
          595.1219512195122
        ]
      ],
      "shape_type": "polygon",
      "flags": {}
    },
    {
      "label": "muddy road",
      "line_color": null,
      "fill_color": null,
      "points": [
        [
          1281.7073170731705,
          581.7073170731707
        ],
        [
          1254.8780487804877,
          567.0731707317073
        ],
        [
          1223.170731707317,
          535.3658536585366
        ],
        [
          1237.8048780487804,
          523.170731707317
        ],
        [
          1289.0243902439024,
          558.5365853658536
        ],
        [
          1297.560975609756,
          569.5121951219512
        ]
      ],
      "shape_type": "polygon",
      "flags": {}
    }
  ],
  "lineColor": [
    0,
    255,
    0,
    128
  ],
  "fillColor": [
    255,
    0,
    0,
    128
  ],
  "imagePath": "Pictures0803_leftImg8bit.png",
  "imageData": null,
  "imageHeight": 1024,
  "imageWidth": 2048
}