{
  "version": "3.16.1",
  "flags": {},
  "shapes": [
    {
      "label": "pothole",
      "line_color": null,
      "fill_color": null,
      "points": [
        [
          420.30434782608694,
          798.5217391304348
        ],
        [
          431.17391304347825,
          763.7391304347825
        ],
        [
          439.8695652173913,
          744.1739130434783
        ],
        [
          513.7826086956521,
          722.4347826086956
        ],
        [
          546.391304347826,
          735.4782608695651
        ],
        [
          533.3478260869565,
          759.391304347826
        ],
        [
          465.95652173913044,
          798.5217391304348
        ]
      ],
      "shape_type": "polygon",
      "flags": {}
    },
    {
      "label": "muddy road",
      "line_color": null,
      "fill_color": null,
      "points": [
        [
          15.95652173913043,
          855.0434782608695
        ],
        [
          0.7391304347826093,
          785.4782608695651
        ],
        [
          535.5217391304348,
          611.5652173913043
        ],
        [
          563.7826086956521,
          581.1304347826086
        ],
        [
          622.4782608695651,
          585.4782608695651
        ],
        [
          626.8260869565217,
          587.6521739130435
        ],
        [
          557.2608695652174,
          633.3043478260869
        ]
      ],
      "shape_type": "polygon",
      "flags": {}
    },
    {
      "label": "side road",
      "line_color": null,
      "fill_color": null,
      "points": [
        [
          0.7391304347826093,
          781.1304347826086
        ],
        [
          20.304347826086953,
          733.3043478260869
        ],
        [
          487.695652173913,
          596.3478260869565
        ],
        [
          533.3478260869565,
          576.7826086956521
        ],
        [
          559.4347826086956,
          581.1304347826086
        ],
        [
          533.3478260869565,
          611.5652173913043
        ]
      ],
      "shape_type": "polygon",
      "flags": {}
    }
  ],
  "lineColor": [
    0,
    255,
    0,
    128
  ],
  "fillColor": [
    255,
    0,
    0,
    128
  ],
  "imagePath": "Pictures0406_leftImg8bit.png",
  "imageData": null,
  "imageHeight": 1024,
  "imageWidth": 2048
}