{
  "version": "3.16.1",
  "flags": {},
  "shapes": [
    {
      "label": "side road",
      "line_color": null,
      "fill_color": null,
      "points": [
        [
          10.88888888888889,
          767.1111111111111
        ],
        [
          499.7777777777777,
          602.6666666666666
        ],
        [
          379.77777777777777,
          593.7777777777777
        ],
        [
          2.0,
          693.7777777777777
        ]
      ],
      "shape_type": "polygon",
      "flags": {}
    },
    {
      "label": "muddy road",
      "line_color": null,
      "fill_color": null,
      "points": [
        [
          8.666666666666664,
          800.4444444444443
        ],
        [
          10.88888888888889,
          767.1111111111111
        ],
        [
          506.44444444444446,
          602.6666666666666
        ],
        [
          550.8888888888889,
          589.3333333333333
        ],
        [
          564.2222222222222,
          589.3333333333333
        ],
        [
          568.6666666666666,
          633.7777777777777
        ],
        [
          566.4444444444445,
          647.1111111111111
        ],
        [
          28.666666666666664,
          1020.4444444444443
        ],
        [
          0,
          1020
        ],
        [
          4.222222222222221,
          949.3333333333333
        ]
      ],
      "shape_type": "polygon",
      "flags": {}
    },
    {
      "label": "waterlog",
      "line_color": null,
      "fill_color": null,
      "points": [
        [
          55.33333333333333,
          809.3333333333333
        ],
        [
          86.44444444444444,
          816.0
        ],
        [
          110.88888888888889,
          816.0
        ],
        [
          137.55555555555554,
          813.7777777777778
        ],
        [
          170.88888888888889,
          809.3333333333333
        ],
        [
          206.44444444444443,
          809.3333333333333
        ],
        [
          224.22222222222223,
          802.6666666666667
        ],
        [
          219.77777777777777,
          784.8888888888889
        ],
        [
          206.44444444444443,
          776.0
        ],
        [
          199.77777777777777,
          762.6666666666666
        ],
        [
          182.0,
          764.8888888888889
        ],
        [
          157.55555555555554,
          769.3333333333333
        ],
        [
          119.77777777777777,
          776.0
        ],
        [
          82.0,
          776.0
        ],
        [
          50.888888888888886,
          778.2222222222222
        ]
      ],
      "shape_type": "polygon",
      "flags": {}
    },
    {
      "label": "waterlog",
      "line_color": null,
      "fill_color": null,
      "points": [
        [
          397.56097560975604,
          663.4146341463414
        ],
        [
          419.5121951219512,
          669.5121951219512
        ],
        [
          440.24390243902434,
          668.2926829268292
        ],
        [
          471.9512195121951,
          668.2926829268292
        ],
        [
          495.12195121951214,
          668.2926829268292
        ],
        [
          513.4146341463414,
          664.6341463414634
        ],
        [
          515.8536585365853,
          656.0975609756097
        ],
        [
          506.0975609756097,
          653.6585365853658
        ],
        [
          486.5853658536585,
          647.560975609756
        ],
        [
          464.6341463414634,
          653.6585365853658
        ],
        [
          449.99999999999994,
          654.8780487804878
        ],
        [
          431.7073170731707,
          654.8780487804878
        ],
        [
          423.17073170731703,
          654.8780487804878
        ]
      ],
      "shape_type": "polygon",
      "flags": {}
    },
    {
      "label": "muddy road",
      "line_color": null,
      "fill_color": null,
      "points": [
        [
          1836.9565217391303,
          1016.5217391304348
        ],
        [
          2041.3043478260868,
          1012.1739130434783
        ],
        [
          993.4782608695651,
          577.391304347826
        ],
        [
          958.695652173913,
          568.695652173913
        ],
        [
          930.4347826086956,
          579.5652173913043
        ]
      ],
      "shape_type": "polygon",
      "flags": {}
    },
    {
      "label": "waterlog",
      "line_color": null,
      "fill_color": null,
      "points": [
        [
          1758.695652173913,
          849.1304347826087
        ],
        [
          1817.391304347826,
          873.0434782608695
        ],
        [
          1908.695652173913,
          890.4347826086955
        ],
        [
          1978.2608695652173,
          914.3478260869565
        ],
        [
          2034.782608695652,
          929.5652173913043
        ],
        [
          2034.782608695652,
          912.1739130434783
        ],
        [
          1930.4347826086955,
          860.0
        ],
        [
          1728.2608695652173,
          801.3043478260869
        ],
        [
          1697.8260869565217,
          801.3043478260869
        ],
        [
          1706.5217391304348,
          829.5652173913043
        ]
      ],
      "shape_type": "polygon",
      "flags": {}
    }
  ],
  "lineColor": [
    0,
    255,
    0,
    128
  ],
  "fillColor": [
    255,
    0,
    0,
    128
  ],
  "imagePath": "Pictures0838_leftImg8bit.png",
  "imageData": null,
  "imageHeight": 1024,
  "imageWidth": 2048
}